ThreeD/Constants.py
ThreeD/__init__.py
ThreeD/threeD.py
TwoD/Constants.py
TwoD/__init__.py
TwoD/twod.py
calculator/__init__.py
calculator/calculate.py
calculate_shapes-0.7.dist-info/LICENSE
calculate_shapes-0.7.dist-info/METADATA
calculate_shapes-0.7.dist-info/WHEEL
calculate_shapes-0.7.dist-info/entry_points.txt
calculate_shapes-0.7.dist-info/top_level.txt
calculate_shapes-0.7.dist-info/RECORD
