Metadata-Version: 2.1
Name: calculate-shapes
Version: 0.7
Summary: Geometry Calculation tool
Home-page: UNKNOWN
Author: Deepesh Ahuja
Author-email: deepeshahuja141291@gmail.com
License: UNKNOWN
Platform: UNKNOWN
Classifier: Programming Language :: Python :: 3
Classifier: License :: OSI Approved :: MIT License
Classifier: Operating System :: OS Independent
Requires-Dist: Click
